{
  "grammar": [
    {
      "name": "いらっしゃいます",
      "level": "N4",
      "tags": [
        "挨拶",
        "尊敬語"
      ],
      "notes": "replacement for 行く, 来る, and いる",
      "example": [
        "「」はいらっしゃいますか",
        "今週末どこへいらっしゃいますか"
      ],
      "gid": "n4-000001"
    },
    {
      "name": "N(名前)＋と申します",
      "level": "N4",
      "tags": [
        "謙譲語",
        "挨拶"
      ],
      "notes": "introducing your name",
      "example": [
        "初めまして、タホと申します"
      ],
      "gid": "n4-000002"
    },
    {
      "name": "参ります",
      "level": "N4",
      "tags": [
        "謙譲語"
      ],
      "notes": "replacement for 行く, and 来る",
      "example": [
        "今年の３月に参りました",
        "今年の１０月に大阪へ参ります"
      ],
      "gid": "n4-000003"
    },
    {
      "name": "普通形＋ので、＿＿＿",
      "level": "N4",
      "tags": [
        "cause-and-effect"
      ],
      "notes": "basic cause and effect",
      "example": [
        "札幌には夢がたくさんあるのでスキーをしたいです",
        "私の犬の種類は「ヒーラー」なので、私はいつも疲れます"
      ],
      "gid": "n4-000004"
    },
    {
      "name": "可能動詞",
      "level": "N4",
      "tags": [
        "可能形"
      ],
      "notes": "「え」る, られる, できる -- basic potential form",
      "example": [
        "私の犬はずっと遊べる",
        "わたしはプログラミングことができる",
        "私は朝早く起きられない"
      ],
      "gid": "n4-000005"
    },
    {
      "name": "N＋なら＿＿＿",
      "level": "N4",
      "tags": [
        "conditions"
      ],
      "notes": "if it's this...",
      "example": [
        "中国の料理は辛物なら食べられない",
        "雨なら、傘を持ってきてください",
        "パソコンなら、マックブックを買うといいです"
      ],
      "gid": "n4-000006"
    },
    {
      "name": "辞書形＋のが＋A",
      "level": "N4",
      "tags": [
        "nominalizing"
      ],
      "notes": "specifically describing an action turned into a noun",
      "example": [
        "アニメを見るのが好きです",
        "スキーをするのが上手です",
        "長い時間に寝るのが嫌いです"
      ],
      "gid": "n4-000007"
    },
    {
      "name": "辞書形＋のは＋A",
      "level": "N4",
      "tags": [
        "nominalizing"
      ],
      "notes": "basic describing an action turned into a noun",
      "example": [
        "ゲームをするのは楽しいです",
        "値段が安いのは、トヨタの車です"
      ],
      "gid": "n4-000008"
    },
    {
      "name": "可能形＋ようになります",
      "level": "N4",
      "tags": [
        "可能形",
        "becoming"
      ],
      "notes": "an action becoming possible",
      "example": [
        "2026までに日本語が話せるようになりたいです",
        "簡単料理が作れるようになりました"
      ],
      "gid": "n4-000009"
    },
    {
      "name": "A＋そうです",
      "level": "N4",
      "tags": [
        "seems"
      ],
      "notes": "how something seems based on your senses",
      "example": [
        "そのゲームは面白そうです",
        "そのホテルは安くなさそうです",
        "私のルームメイトは静かじゃなさそうです"
      ],
      "gid": "n4-000010"
    },
    {
      "name": "テ形＋みます",
      "level": "N4",
      "tags": [
        "combo"
      ],
      "notes": "try something",
      "example": [
        "あの山を登ってみます",
        "この上着を着てみたいです"
      ],
      "gid": "n4-000011"
    },
    {
      "name": "テ形＋もらえませんか",
      "level": "N4",
      "tags": [
        "丁寧語",
        "receiving-and-giving"
      ],
      "notes": "receiving a favor",
      "example": [
        "光を消えてもらえませんか",
        "結婚式の写真を見せてもらえませんか"
      ],
      "gid": "n4-000012"
    },
    {
      "name": "A＋すぎます",
      "level": "N4",
      "tags": [
        "combo"
      ],
      "notes": "describing something as too much",
      "example": [
        "ボストンには私のアパートが高すぎました"
      ],
      "gid": "n4-000013"
    },
    {
      "name": "マス形＋すぎます",
      "level": "N4",
      "tags": [
        "combo"
      ],
      "notes": "something you did too much of",
      "example": [
        "私は食べすぎました"
      ],
      "gid": "n4-000014"
    },
    {
      "name": "マス形＋やすいです",
      "level": "N4",
      "tags": [
        "combo"
      ],
      "notes": "describing something as too easy",
      "example": [
        "この小説は読みやすいです"
      ],
      "gid": "n4-000015"
    },
    {
      "name": "マス形＋にくいです",
      "level": "N4",
      "tags": [
        "combo"
      ],
      "notes": "describing something as too hard",
      "example": [
        "日本語の宿題が多いですから、プログラミングをしにくいです"
      ],
      "gid": "n4-000016"
    },
    {
      "name": "テ形＋あります",
      "level": "N4",
      "tags": [
        "combo"
      ],
      "notes": "after an action was done and left by someone",
      "example": [
        "駅の近くに地図が貼ってあります"
      ],
      "gid": "n4-000017"
    },
    {
      "name": "何と読みますかー「」と読みます",
      "level": "N4",
      "tags": [
        "疑問形"
      ],
      "notes": "asking/describing how to read something",
      "example": [
        "これは何と読みますか",
        "「」と読みますよ"
      ],
      "gid": "n4-000018"
    },
    {
      "name": "「」と書いてあります",
      "level": "N4",
      "tags": [
        "疑問形",
        "combo"
      ],
      "notes": "after a writing action was done and left by someone",
      "example": [
        "「」と書いてあります"
      ],
      "gid": "n4-000019"
    },
    {
      "name": "どういう意味ですかー普通形＋という意味です",
      "level": "N4",
      "tags": [
        "疑問形"
      ],
      "notes": "asking/describing the meaning of a word",
      "example": [
        "「」はどういう意味ですか",
        "「」と言う意味です",
        "。。。だと言う意味です"
      ],
      "gid": "n4-000020"
    },
    {
      "name": "N＋にします",
      "level": "N4",
      "tags": [
        "conditions"
      ],
      "notes": "ordering/choosing a specific thing",
      "example": [
        "からあげのセットにします",
        "このレストランにしましょう"
      ],
      "gid": "n4-000021"
    },
    {
      "name": "マス形＋すぎです",
      "level": "N4",
      "tags": [
        "combo"
      ],
      "notes": "pointing out something someone else did too much",
      "example": [
        "ソダさん、飲みすぎですよ"
      ],
      "gid": "n4-000022"
    },
    {
      "name": "タ形＋ら、＿＿＿",
      "level": "N4",
      "tags": [
        "conditions"
      ],
      "notes": "once this happens, ...",
      "example": [
        "日本語学校を卒業したら、日本の会社で働きたいです",
        "夏休みになったら、新しい本を読む",
        "コンサートに行ったら、人がたくさん並んでいました",
        "区役所へ行ったら、誰もいませんでした",
        "今週末電話したらどうですか"
      ],
      "gid": "n4-000023"
    },
    {
      "name": "意向形＋と思っています",
      "level": "N4",
      "tags": [
        "probability",
        "sure-and-unsure"
      ],
      "notes": "80% sure",
      "example": [
        "今週末日本語の聴解を練習しようと思っています"
      ],
      "gid": "n4-000024"
    },
    {
      "name": "辞書形＋つもりです",
      "level": "N4",
      "tags": [
        "probability",
        "sure-and-unsure"
      ],
      "notes": "120% sure",
      "example": [
        "8月に友達と一緒に大阪へ行くつもりです"
      ],
      "gid": "n4-000025"
    },
    {
      "name": "ナイ形＋つもりです",
      "level": "N4",
      "tags": [
        "probability",
        "sure-and-unsure"
      ],
      "notes": "120% sure",
      "example": [
        "今年私の母国へ帰らないつもりです"
      ],
      "gid": "n4-000026"
    },
    {
      "name": "疑問詞＋普通形＋か、＿＿＿",
      "level": "N4",
      "tags": [
        "sure-and-unsure",
        "疑問形"
      ],
      "notes": "unsure of a question",
      "example": [
        "どの会社がいいか、調べます",
        "何を食べるか、まだ決めていません"
      ],
      "gid": "n4-000027"
    },
    {
      "name": "普通形＋かどうか、＿＿＿",
      "level": "N4",
      "tags": [
        "sure-and-unsure",
        "疑問形"
      ],
      "notes": "unsure of a fact",
      "example": [
        "母国へ帰るかどうか、まだ決めていません",
        "ホテルを予約するかどうか、確認します"
      ],
      "gid": "n4-000028"
    },
    {
      "name": "N＋のために、＿＿＿",
      "level": "N4",
      "tags": [
        "cause-and-effect"
      ],
      "notes": "purpose/reason for something",
      "example": [
        "就職のために、毎日プログラミングを練習しています"
      ],
      "gid": "n4-000029"
    },
    {
      "name": "辞書形＋ために、＿＿＿",
      "level": "N4",
      "tags": [
        "cause-and-effect"
      ],
      "notes": "purpose/reason for something",
      "example": [
        "日本語を話すために、日本に来た"
      ],
      "gid": "n4-000030"
    },
    {
      "name": "普通形＋んです",
      "level": "N4",
      "tags": [
        "疑問形",
        "explaining"
      ],
      "notes": "adding extra information/explaining",
      "example": [
        "ソダさんはこの本を読んだんですか",
        "あれはソダさんの？",
        "それを食べているんですか",
        "どうして日本に来たんですか",
        "何してんだよ"
      ],
      "gid": "n4-000031"
    },
    {
      "name": "ナイ形＋ければなりません",
      "level": "N4",
      "tags": [
        "set-phrase",
        "conditions",
        "丁寧語",
        "combo"
      ],
      "notes": "must not do",
      "example": [
        "金曜日までに宿題をしなければなりません",
        "母は私に野菜を食べなければなりませんと言っていました",
        "クラスのベルが鳴る前に来ることになっています",
        "今冬両親の家へ行かないことになっているんです"
      ],
      "gid": "n4-000032"
    },
    {
      "name": "普通形＋んですが、＿＿＿",
      "level": "N4",
      "tags": [
        "疑問形",
        "explaining",
        "sentence-connector"
      ],
      "notes": "giving a reason for an incoming question / topic switch",
      "example": [
        "今冬スキーをしたいんですが、一緒に行きませんか",
        "卒業をしたら、日本の会社で働きたいんですが、いい会社を紹介してもらえませんか"
      ],
      "gid": "n4-000033"
    },
    {
      "name": "普通形＋なら、＿＿＿",
      "level": "N4",
      "tags": [
        "conditions"
      ],
      "notes": "if it's this",
      "example": [
        "日本語のが話せるようになりたいなら、毎日小説を読むのがいいですよ"
      ],
      "gid": "n4-000034"
    },
    {
      "name": "タ形＋らしいです",
      "level": "N4",
      "tags": [
        "probability",
        "sure-and-unsure"
      ],
      "notes": "rumors / something you heard from someone",
      "example": [
        "彼は昨日、映画を見たらしい"
      ],
      "gid": "n4-000035"
    },
    {
      "name": "辞書形＋といいです",
      "level": "N4",
      "tags": [
        "conditions",
        "recommendations"
      ],
      "notes": "giving advice",
      "example": [
        "スキーをしたいので、札幌へ行くといいです",
        "この食べ物は辛いので、牛乳を飲むといいです"
      ],
      "gid": "n4-000036"
    },
    {
      "name": "N＋までに＿＿＿",
      "level": "N4",
      "tags": [
        "time",
        "conditions"
      ],
      "notes": "deadline",
      "example": [
        "2026までに日本語のが話せなければなりません",
        "今週末までにチケットを買わなければなりません"
      ],
      "gid": "n4-000037"
    },
    {
      "name": "辞書形＋と、N＋があります",
      "level": "N4",
      "tags": [
        "location",
        "conditions"
      ],
      "notes": "giving directions",
      "example": [
        "駅から5分くらいまっすぐ歩くと、右に私のアパートがあります"
      ],
      "gid": "n4-000038"
    },
    {
      "name": "N＋じゃなくて、＿＿＿",
      "level": "N4",
      "tags": [
        "conditions"
      ],
      "notes": "correcting someone",
      "example": [
        "ウイリアムじゃなくて、タホですよ",
        "オーストラリア人じゃなくて、アメリカ人です"
      ],
      "gid": "n4-000039"
    },
    {
      "name": "辞書形+んじゃなくて、＿＿＿",
      "level": "N4",
      "tags": [
        "conditions"
      ],
      "notes": "correcting someone",
      "example": [
        "彼は行くんじゃなくて、帰るんです"
      ],
      "gid": "n4-000040"
    },
    {
      "name": "A＋なら、＿＿＿",
      "level": "N4",
      "tags": [
        "conditions"
      ],
      "notes": "if it's this...",
      "example": [
        "暑いなら、セーターを持っていってください"
      ],
      "gid": "n4-000041"
    },
    {
      "name": "N＋なら、＿＿＿",
      "level": "N4",
      "tags": [
        "conditions"
      ],
      "notes": "if it's this...",
      "example": [
        "日本語なら、私が読みます"
      ],
      "gid": "n4-000042"
    },
    {
      "name": "テ形＋しまいました",
      "level": "N4",
      "tags": [
        "combo",
        "explaining"
      ],
      "notes": "accidentally or unexpected, in advance",
      "example": [
        "傘を忘れてしまいました",
        "スマホを落としちゃった",
        "ご飯を食べてしまいます",
        "部屋を掃除してしまいます"
      ],
      "gid": "n4-000043"
    },
    {
      "name": "普通形＋かもしれません",
      "level": "N4",
      "tags": [
        "probability",
        "sure-and-unsure"
      ],
      "notes": "50% unsure",
      "example": [
        "来年の夏に私の両親は日本へ来るかもしれません"
      ],
      "gid": "n4-000044"
    },
    {
      "name": "N＋のあとで、＿＿＿",
      "level": "N4",
      "tags": [
        "time",
        "conditions"
      ],
      "notes": "after this ...",
      "example": [
        "卒業のあとで、会社で働き始めた"
      ],
      "gid": "n4-000045"
    },
    {
      "name": "タ形＋あとで、＿＿＿",
      "level": "N4",
      "tags": [
        "time",
        "conditions"
      ],
      "notes": "after this...",
      "example": [
        "クラスが終わったあとで、買い物をしよう",
        "家に帰ったあとで、シャワーを浴びました"
      ],
      "gid": "n4-000046"
    },
    {
      "name": "テ形＋いただけませんか",
      "level": "N4",
      "tags": [
        "敬語",
        "receiving-and-giving"
      ],
      "notes": "humble form of もらう (to receive)",
      "example": [
        "漢字の書き方を教えていただけませんか"
      ],
      "gid": "n4-000047"
    },
    {
      "name": "A＋(くて|で)、＿＿＿",
      "level": "N4",
      "tags": [
        "sentence-connector"
      ],
      "notes": "connects two ideas with adjectives",
      "example": [
        "このケーキは甘くて、おいしいです",
        "この部屋は静かで、広いです"
      ],
      "gid": "n4-000048"
    },
    {
      "name": "テ形、＿＿＿",
      "level": "N4",
      "tags": [
        "cause-and-effect",
        "sentence-connector"
      ],
      "notes": "giving a reason for what comes next",
      "example": [
        "自転車が盗まれて、遅れました",
        "お酒を飲みすぎて、二日酔いです"
      ],
      "gid": "n4-000049"
    },
    {
      "name": "ナイ形＋くて、＿＿＿",
      "level": "N4",
      "tags": [
        "sentence-connector"
      ],
      "notes": "connecting a negative quality with the rest of a sentence",
      "example": [
        "この問題は難しくなくて、簡単です"
      ],
      "gid": "n4-000050"
    },
    {
      "name": "タ形＋ら、＿＿＿タ形",
      "level": "N4",
      "tags": [
        "conditions",
        "becoming",
        "sentence-connector"
      ],
      "notes": "once this happened, ...",
      "example": [
        "カバンを開けたら、財布がありませんでした"
      ],
      "gid": "n4-000051"
    },
    {
      "name": "マス形＋ましょうか",
      "level": "N4",
      "tags": [
        "丁寧語",
        "combo",
        "favors"
      ],
      "notes": "invitation or request to do by yourself",
      "example": [
        "レストランに行きましょうか",
        "家を掃除しましょうか"
      ],
      "gid": "n4-000052"
    },
    {
      "name": "普通形＋し、＿＿＿",
      "level": "N4",
      "tags": [
        "lists",
        "sentence-connector"
      ],
      "notes": "listing actions",
      "example": [
        "東京になたくさん店もあるし、美味しい食べ物も食べるし、安いホテルもある"
      ],
      "gid": "n4-000053"
    },
    {
      "name": "普通形＋のは＋N＋です",
      "level": "N4",
      "tags": [
        "explaining"
      ],
      "notes": "used to choose an option or give an answer",
      "example": [
        "車の値段が安いのはホンダです"
      ],
      "gid": "n4-000054"
    },
    {
      "name": "A＋そうです",
      "level": "N4",
      "tags": [
        "seems"
      ],
      "notes": "how something seems based on your senses",
      "example": [
        "この図書館は静かそうです",
        "このホテルは安そうです"
      ],
      "gid": "n4-000055"
    },
    {
      "name": "マス形(-ます)＋そうです",
      "level": "N4",
      "tags": [
        "seems"
      ],
      "notes": "how something seems based on your senses",
      "example": [
        "深夜雨が降りそうです",
        "秋の間に京都が混みそうです",
        "皿が落ちそうです",
        "ゴミ袋を破れそうです"
      ],
      "gid": "n4-000056"
    },
    {
      "name": "マス形(-ます)＋そう(に|も|にも)ありません",
      "level": "N4",
      "tags": [
        "seems"
      ],
      "notes": "how something seems based on your senses",
      "example": [
        "彼は勝ちそうにありません"
      ],
      "gid": "n4-000057"
    },
    {
      "name": "テ形＋おきます",
      "level": "N4",
      "tags": [
        "combo"
      ],
      "notes": "do something in advance, leave in place",
      "example": [
        "クラスの前にカバンをまとめておきます",
        "ビールを冷蔵庫に入れておきます",
        "そのままにしておきます"
      ],
      "gid": "n4-000058"
    },
    {
      "name": "テ形＋あります",
      "level": "N4",
      "tags": [
        "combo"
      ],
      "notes": "already finished",
      "example": [
        "もう宿題を終わってあります"
      ],
      "gid": "n4-000059"
    },
    {
      "name": "お＋マス形＋になります",
      "level": "N4",
      "tags": [
        "敬語",
        "combo",
        "set-phrase"
      ],
      "notes": "create keigo out of any verb",
      "example": [
        "どちらそれをお買いになりましたか"
      ],
      "gid": "n4-000060"
    },
    {
      "name": "尊敬動詞(受身形)",
      "level": "N4",
      "tags": [
        "尊敬語"
      ],
      "notes": "create sonkeigo out of basic verbs",
      "example": [
        "タホさんは全部たべられました",
        "みんなさん映画へ行かれました",
        "ソダさんよく釣りをされる"
      ],
      "gid": "n4-000061"
    },
    {
      "name": "尊敬語(行く|来る|いる)",
      "level": "N4",
      "tags": [
        "尊敬語"
      ],
      "notes": "replacement for 行く, 来る, and いる",
      "example": [
        "部長はいらっしゃいますか"
      ],
      "gid": "n4-000062"
    },
    {
      "name": "尊敬語(食べる|飲む)",
      "level": "N4",
      "tags": [
        "尊敬語"
      ],
      "notes": "replacement for 食べる, and 飲む",
      "example": [
        "もうご飯を召し上がりましたか"
      ],
      "gid": "n4-000063"
    },
    {
      "name": "尊敬語(くれる)",
      "level": "N4",
      "tags": [
        "尊敬語"
      ],
      "notes": "replacement for くれる",
      "example": [
        "こちらでお待ちください",
        "ご注意ください"
      ],
      "gid": "n4-000064"
    },
    {
      "name": "尊敬語(言う)",
      "level": "N4",
      "tags": [
        "尊敬語"
      ],
      "notes": "replacement for 言う",
      "example": [
        "お母さんは帰りなさいとおっしゃいました"
      ],
      "gid": "n4-000065"
    },
    {
      "name": "尊敬語(する)",
      "level": "N4",
      "tags": [
        "尊敬語"
      ],
      "notes": "replacement for する",
      "example": [
        "今冬スキーをなさりますか"
      ],
      "gid": "n4-000066"
    },
    {
      "name": "尊敬語(見る)",
      "level": "N4",
      "tags": [
        "尊敬語"
      ],
      "notes": "replacement for 見る",
      "example": [
        "映画をご覧になりましたか"
      ],
      "gid": "n4-000067"
    },
    {
      "name": "尊敬語(知っている)",
      "level": "N4",
      "tags": [
        "尊敬語"
      ],
      "notes": "replacement for 知っている",
      "example": [
        "このアニメをご存じですか"
      ],
      "gid": "n4-000068"
    },
    {
      "name": "尊敬語(etc.)",
      "level": "N4",
      "tags": [
        "尊敬語"
      ],
      "notes": "other various sonkeigo phrases",
      "example": [
        "日本の生活はいかがですか",
        "どちらいらっしゃいますか",
        "どなたこれを召し上がりましたか"
      ],
      "gid": "n4-000069"
    },
    {
      "name": "ご＋N＋します",
      "level": "N4",
      "tags": [
        "謙譲語"
      ],
      "notes": "creating kenjougo from nouns",
      "example": [
        "奥さんをご紹介します"
      ],
      "gid": "n4-000070"
    },
    {
      "name": "お＋マス形＋します",
      "level": "N4",
      "tags": [
        "謙譲語"
      ],
      "notes": "creating kenjougo from verbs",
      "example": [
        "ソダさん、お手伝いしましょうか",
        "荷物をお待ちします"
      ],
      "gid": "n4-000071"
    },
    {
      "name": "イA＋く＋V",
      "level": "N4",
      "tags": [
        "combo"
      ],
      "notes": "creating a basic adverb",
      "example": [
        "野菜を薄く切ります"
      ],
      "gid": "n4-000072"
    },
    {
      "name": "(ナA|N)＋に＋V",
      "level": "N4",
      "tags": [
        "combo"
      ],
      "notes": "creating a basic adverb",
      "example": [
        "彼は静かに勉強している",
        "野菜を半分に切ります",
        "火を弱火にしてください"
      ],
      "gid": "n4-000073"
    },
    {
      "name": "テ形＋いる＋間に、＿＿＿",
      "level": "N4",
      "tags": [
        "time"
      ],
      "notes": "while",
      "example": [
        "肉を焼きている間に、ビールを飲む"
      ],
      "gid": "n4-000074"
    },
    {
      "name": "人＋に＋テ形＋あげます",
      "level": "N4",
      "tags": [
        "receiving-and-giving"
      ],
      "notes": "does it for に/を",
      "example": [
        "ソダさんはタホに釣り旅行の写真を見せてあげます",
        "ソダさんはタホを奥多摩へ連れて行ってあげました",
        "タホさんは両親のテレビを治してあげました"
      ],
      "gid": "n4-000075"
    },
    {
      "name": "人＋に＋テ形＋もらいます",
      "level": "N4",
      "tags": [
        "receiving-and-giving"
      ],
      "notes": "receives from に",
      "example": [
        "タホさんはソダさんに中国語を教えてもらいました"
      ],
      "gid": "n4-000076"
    },
    {
      "name": "人＋に＋テ形＋くれます",
      "level": "N4",
      "tags": [
        "receiving-and-giving"
      ],
      "notes": "does it for the speaker (dropped  に usually)",
      "example": [
        "ソダさんが釣り旅行の写真を見せてくれました"
      ],
      "gid": "n4-000077"
    },
    {
      "name": "人＋に＋物＋をいただきます",
      "level": "N4",
      "tags": [
        "receiving-and-giving"
      ],
      "notes": "receives from に",
      "example": [
        "私は誕生日プレゼントをいただきました"
      ],
      "gid": "n4-000078"
    },
    {
      "name": "人＋に＋物＋をくださいます",
      "level": "N4",
      "tags": [
        "receiving-and-giving"
      ],
      "notes": "does it for に",
      "example": [
        "ソダさんが誕生日プレゼントをくださいました"
      ],
      "gid": "n4-000079"
    },
    {
      "name": "人＋に＋テ形＋いただきます",
      "level": "N4",
      "tags": [
        "receiving-and-giving"
      ],
      "notes": "receives from に",
      "example": [
        "私は母に料理を教えていただきました"
      ],
      "gid": "n4-000080"
    },
    {
      "name": "人＋に＋テ形＋くださいます",
      "level": "N4",
      "tags": [
        "receiving-and-giving"
      ],
      "notes": "does it for に",
      "example": [
        "ソダさんが私に釣り方を教えてくださいました"
      ],
      "gid": "n4-000081"
    },
    {
      "name": "(V|イA)条件形、＿＿＿",
      "level": "N4",
      "tags": [
        "conditions"
      ],
      "notes": "if it's this...",
      "example": [
        "毎日勉強すれば、日本語能力試験を合格できます",
        "寒ければ、手袋を持ってきてください",
        "日本語が分からなければ、日本に住むのは難しいです",
        "質問があれば、先生に聞いてください"
      ],
      "gid": "n4-000082"
    },
    {
      "name": "(ナA|N)条件形、＿＿＿",
      "level": "N4",
      "tags": [
        "conditions"
      ],
      "notes": "if it's this...",
      "example": [
        "明日なら、空いています",
        "時間があるなら、一緒に映画を見に行きましょう"
      ],
      "gid": "n4-000083"
    },
    {
      "name": "(辞書|ナイ)形＋ように、＿＿＿",
      "level": "N4",
      "tags": [
        "becoming"
      ],
      "notes": "so that ... happens",
      "example": [
        "忘れないように毎日勉強します",
        "タオル流を早く乾くように外に掛ける"
      ],
      "gid": "n4-000084"
    },
    {
      "name": "(辞書|ナイ)形＋ようにしてください",
      "level": "N4",
      "tags": [
        "becoming"
      ],
      "notes": "so that ... happens as a command",
      "example": [
        "廊下に走らないようにしてください",
        "質問があれば、先生に聞くようにしてください"
      ],
      "gid": "n4-000085"
    },
    {
      "name": "(辞書|ナイ)形＋ことになっています",
      "level": "N4",
      "tags": [
        "becoming"
      ],
      "notes": "something has been decided (plan, rules) out of your control",
      "example": [
        "来月から東京に転勤することになっています",
        "ここでは写真を撮らないことになっています"
      ],
      "gid": "n4-000086"
    },
    {
      "name": "ご＋N＋ください",
      "level": "N4",
      "tags": [
        "謙譲語"
      ],
      "notes": "creating kenjougo from nouns",
      "example": [
        "ご注意ください",
        "ご覧ください"
      ],
      "gid": "n4-000087"
    },
    {
      "name": "お＋マス形＋ください",
      "level": "N4",
      "tags": [
        "謙譲語"
      ],
      "notes": "creating kenjougo from verbs",
      "example": [
        "お待ちください"
      ],
      "gid": "n4-000088"
    },
    {
      "name": "V[ましょう]の友達言葉",
      "level": "N4",
      "tags": [
        "意向形"
      ],
      "notes": "a friendlier version of ましょう",
      "example": [
        "食べよう",
        "行こう"
      ],
      "gid": "n4-000089"
    },
    {
      "name": "受身形",
      "level": "N4",
      "tags": [
        "receiving-and-giving",
        "passive"
      ],
      "notes": "to be done by; subject is receiver",
      "example": [
        "タホさんは先生に呼ばれました",
        "私は知らない人に質問を聞かれた",
        "財布を盗まれた",
        "今週末からチケットは買われる",
        "ハリーポッターはJKローランによって書かれました"
      ],
      "gid": "n4-000090"
    },
    {
      "name": "辞書形＋のに、＿＿＿",
      "level": "N4",
      "tags": [
        "cause-and-effect",
        "sentence-connector"
      ],
      "notes": "in order to",
      "example": [
        "野菜ジュースを作るのに便利です",
        "この靴は山を登るのにいいです"
      ],
      "gid": "n4-000091"
    },
    {
      "name": "普通形＋ようです",
      "level": "N4",
      "tags": [
        "seems"
      ],
      "notes": "seems like but with more emphasis on speakers own conclusion",
      "example": [
        "電車の事故があったようです",
        "雨のようです",
        "このレストランのラーメンを美味しいようです"
      ],
      "gid": "n4-000092"
    },
    {
      "name": "普通形＋みたいです",
      "level": "N4",
      "tags": [
        "seems"
      ],
      "notes": "how something seems based on direct observation, casually; looks like a",
      "example": [
        "その食べ物は美味しいみたいです",
        "学校みたいな建物です",
        "コンサートが始まるみたいだ",
        "このジュースが健康みたいです"
      ],
      "gid": "n4-000093"
    },
    {
      "name": "(辞書形|テ形いる|タ形)＋ところです",
      "level": "N4",
      "tags": [
        "time"
      ],
      "notes": "just before, during, or immediately after",
      "example": [
        "雨が降るところです",
        "晩ご飯を作っているところです",
        "宿題を終わったところです"
      ],
      "gid": "n4-000094"
    },
    {
      "name": "N＋が＋テ形＋きます",
      "level": "N4",
      "tags": [
        "combo",
        "location"
      ],
      "notes": "coming towards",
      "example": [
        "あの鳥が飛んできました",
        "先生が入ってきます"
      ],
      "gid": "n4-000095"
    },
    {
      "name": "N＋が＋テ形＋いきます",
      "level": "N4",
      "tags": [
        "combo",
        "location"
      ],
      "notes": "going away",
      "example": [
        "犬が走っていきます"
      ],
      "gid": "n4-000096"
    },
    {
      "name": "A＋そうに＋V",
      "level": "N4",
      "tags": [
        "seems"
      ],
      "notes": "in a way that seems like; seems to be",
      "example": [
        "子供たちは楽しそうに遊んでいます",
        "ソダさんが心配そうに待っています"
      ],
      "gid": "n4-000097"
    },
    {
      "name": "辞書形＋ようになります",
      "level": "N4",
      "tags": [
        "set-phrase",
        "becoming"
      ],
      "notes": "new habit or ability, change over time",
      "example": [
        "最近たくさんアニメを見るようになりました"
      ],
      "gid": "n4-000098"
    },
    {
      "name": "ナイ形＋くなります",
      "level": "N4",
      "tags": [
        "becoming"
      ],
      "notes": "decrease in frequency, quantity; becoming less",
      "example": [
        "最近お酒を飲まなくなりました"
      ],
      "gid": "n4-000099"
    },
    {
      "name": "タ形＋ばかりです",
      "level": "N4",
      "tags": [
        "time"
      ],
      "notes": "just finished",
      "example": [
        "日本に来たばかりです",
        "アルバイトを始めたばかりなので、まだ仕事に慣れません",
        "仕事を辞めたばかりなのに、もう新しい仕事を見つけた"
      ],
      "gid": "n4-000100"
    },
    {
      "name": "マス形＋ながら、＿＿＿",
      "level": "N4",
      "tags": [
        "combo",
        "sentence-connector"
      ],
      "notes": "doing two things at once",
      "example": [
        "歩きながら、食べている",
        "仕事をしながら、日本語を勉強している"
      ],
      "gid": "n4-000101"
    },
    {
      "name": "普通形＋と言っていました",
      "level": "N4",
      "tags": [
        "nominalizing",
        "set-phrase"
      ],
      "notes": "quoting something said",
      "example": [
        "彼がそのレストランはいいと言っていました",
        "彼はスポーツが好きだと言っていました",
        "先生が明日は休むと言っていました"
      ],
      "gid": "n4-000102"
    },
    {
      "name": "命令形",
      "level": "N4",
      "tags": [
        "command"
      ],
      "notes": "positive command; super casual",
      "example": [
        "走れ",
        "行け"
      ],
      "gid": "n4-000103"
    },
    {
      "name": "辞書形な",
      "level": "N4",
      "tags": [
        "command"
      ],
      "notes": "negative command; super casual",
      "example": [
        "諦めるな"
      ],
      "gid": "n4-000104"
    },
    {
      "name": "〜個＋も＋V",
      "level": "N4",
      "tags": [
        "counting"
      ],
      "notes": "surprise at a high number",
      "example": [
        "お酒は6杯も飲みました"
      ],
      "gid": "n4-000105"
    },
    {
      "name": "(〜個|N)＋しか＋V[ません]",
      "level": "N4",
      "tags": [
        "counting"
      ],
      "notes": "surprise at a low number",
      "example": [
        "昨日は3時間しか寝られなかった",
        "週末しか自分で料理を作らない"
      ],
      "gid": "n4-000106"
    },
    {
      "name": "ナイ形＋で、＿＿＿",
      "level": "N4",
      "tags": [
        "recommendations",
        "command",
        "sentence-connector"
      ],
      "notes": "don't do this, do that",
      "example": [
        "毎日肉を食べないで、時々豆腐を食べます"
      ],
      "gid": "n4-000107"
    },
    {
      "name": "テ形＋V",
      "level": "N4",
      "tags": [
        "combo",
        "conditions"
      ],
      "notes": "an action that involves two",
      "example": [
        "砂糖を入れて飲めます"
      ],
      "gid": "n4-000108"
    },
    {
      "name": "ナイ形＋で＋V",
      "level": "N4",
      "tags": [
        "combo",
        "conditions"
      ],
      "notes": "an action that involves two, negatively",
      "example": [
        "砂糖を入れないで飲めません"
      ],
      "gid": "n4-000109"
    },
    {
      "name": "タ形＋らどうですか",
      "level": "N4",
      "tags": [
        "recommendations",
        "set-phrase"
      ],
      "notes": "what about this",
      "example": [
        "留学生の就職について話を聞くのはどうですか"
      ],
      "gid": "n4-000110"
    },
    {
      "name": "普通形＋らしいです",
      "level": "N4",
      "tags": [
        "sure-and-unsure",
        "explaining",
        "set-phrase"
      ],
      "notes": "a rumor you heard, something people say",
      "example": [
        "プロテインは体にいいらしいです",
        "二日酔いだとたくさん寝るはいいらしいです",
        "5時午後からそのレストランは無料らしいです"
      ],
      "gid": "n4-000111"
    },
    {
      "name": "N＋に、＿＿＿",
      "level": "N4",
      "tags": [
        "sentence-connector",
        "conditions"
      ],
      "notes": "for this specifically, in order to",
      "example": [
        "この食べ物はダイエットにいいです"
      ],
      "gid": "n4-000112"
    },
    {
      "name": "普通形＋のに、＿＿＿",
      "level": "N4",
      "tags": [
        "sentence-connector",
        "conditions"
      ],
      "notes": "even though ___",
      "example": [
        "毎日聴解を練習したのに、日本語が聞き取らない"
      ],
      "gid": "n4-000113"
    },
    {
      "name": "(辞書形|ナイ形)＋ようにしています",
      "level": "N4",
      "tags": [
        "becoming",
        "set-phrase"
      ],
      "notes": "effort, habit, goal that has started or quit",
      "example": [
        "私はできるだけ毎日勉強するようにしている",
        "たくさんテレビを見ないようにしています"
      ],
      "gid": "n4-000114"
    },
    {
      "name": "(辞書形|ナイ形)＋ことにします",
      "level": "N4",
      "tags": [
        "set-phrase",
        "becoming"
      ],
      "notes": "a choice, resolution to do something",
      "example": [
        "多すぎるお酒を飲まないことにします",
        "スポーツジムを通うことにします"
      ],
      "gid": "n4-000115"
    },
    {
      "name": "使役動詞",
      "level": "N4",
      "tags": [
        "cause-and-effect",
        "receiving-and-giving"
      ],
      "notes": "basic causative, に receives the command",
      "example": [
        "親は子供を塾に通わせます",
        "親は子供に野菜を食べさせます",
        "母親は娘に好きなものを買わせます"
      ],
      "gid": "n4-000116"
    },
    {
      "name": "使役受身",
      "level": "N4",
      "tags": [
        "cause-and-effect",
        "receiving-and-giving"
      ],
      "notes": "was caused, に gives the command",
      "example": [
        "私は妻にタバコをやめさせられました",
        "私は先輩に酒を飲まされた"
      ],
      "gid": "n4-000117"
    },
    {
      "name": "使役動詞テ形＋(くれます|もらいます)",
      "level": "N4",
      "tags": [
        "cause-and-effect",
        "receiving-and-giving",
        "丁寧語"
      ],
      "notes": "was told to as a favor / was given permission; に is the grantor",
      "example": [
        "母は私に日本語を習わせてくれました",
        "私は母に外で遊ばせてくれませんでした",
        "私は先輩に小説を買わせてもらいました"
      ],
      "gid": "n4-000118"
    },
    {
      "name": "(辞書形|テ形いる|タ形)＋のを見ました",
      "level": "N4",
      "tags": [
        "becoming",
        "seems",
        "set-phrase",
        "explaining",
        "habits"
      ],
      "notes": "something seen happening recently",
      "example": [
        "子供たちが公園で元気に遊んでいるのを見ました"
      ],
      "gid": "n4-000119"
    },
    {
      "name": "テ形＋いました",
      "level": "N4",
      "tags": [
        "explaining",
        "combo",
        "habits"
      ],
      "notes": "something that used to happen",
      "example": [
        "子供の頃、毎日友達と遊んでいました"
      ],
      "gid": "n4-000120"
    },
    {
      "name": "N＋ばかり＋テ形＋います",
      "level": "N4",
      "tags": [
        "explaining",
        "habits"
      ],
      "notes": "negative emphasis on something only happening",
      "example": [
        "ゲームばかりしています"
      ],
      "gid": "n4-000121"
    },
    {
      "name": "テ形＋ばかりいます",
      "level": "N4",
      "tags": [
        "explaining",
        "habits"
      ],
      "notes": "negative emphasis on something only happening",
      "example": [
        "ゲームをしてばかりいます"
      ],
      "gid": "n4-000122"
    },
    {
      "name": "N＋って何ですか",
      "level": "N4",
      "tags": [
        "疑問形",
        "explaining",
        "nominalizing"
      ],
      "notes": "casual way of saying と when quoting",
      "example": [
        "水族館って何ですか"
      ],
      "gid": "n4-000123"
    },
    {
      "name": "N＋というのは＋＿＿＿です",
      "level": "N4",
      "tags": [
        "explaining",
        "nominalizing"
      ],
      "notes": "describing something said, rephrasing",
      "example": [
        "ランドセルというのは小学生が使うカバンです"
      ],
      "gid": "n4-000124"
    },
    {
      "name": "普通形＋と言われています",
      "level": "N4",
      "tags": [
        "nominalizing",
        "explaining",
        "set-phrase"
      ],
      "notes": "a rumor you heard, something people say",
      "example": [
        "ニンジンは目にいいと言われています"
      ],
      "gid": "n4-000125"
    },
    {
      "name": "N＋のような＋N",
      "level": "N4",
      "tags": [
        "describing",
        "comparisons"
      ],
      "notes": "explaining as a type of something similiar",
      "example": [
        "将棋というのはギターのような楽器です"
      ],
      "gid": "n4-000126"
    },
    {
      "name": "(普通形|意向形)＋かな",
      "level": "N4",
      "tags": [
        "sure-and-unsure",
        "疑問形"
      ],
      "notes": "wondering something to yourself",
      "example": [
        "今夜どこへ行こうかな",
        "何を買おうかな"
      ],
      "gid": "n4-000127"
    },
    {
      "name": "N＋なんかどうですか",
      "level": "N4",
      "tags": [
        "conditions",
        "recommendations",
        "疑問形"
      ],
      "notes": "what about this",
      "example": [
        "恋人のプレゼントなら、時計なんかどうですか"
      ],
      "gid": "n4-000128"
    },
    {
      "name": "A＋がっています",
      "level": "N4",
      "tags": [
        "explaining",
        "combo"
      ],
      "notes": "a third persons feelings not in the conversation",
      "example": [
        "弟はドイツへ行きたがっている",
        "母は新しい車を欲しがっている"
      ],
      "gid": "n4-000129"
    },
    {
      "name": "普通形＋からです",
      "level": "N4",
      "tags": [
        "explaining",
        "cause-and-effect"
      ],
      "notes": "giving a reason at the end of a sentence",
      "example": [
        "祖母にカメの置物をあげました、カメは長生きのシンボルからです"
      ],
      "gid": "n4-000130"
    },
    {
      "name": "普通形＋んだって",
      "level": "N4",
      "tags": [
        "explaining"
      ],
      "notes": "explaining something you saw",
      "example": [
        "インダーネットで調べたんだけど、今週末花火があるんだって"
      ],
      "gid": "n4-000131"
    },
    {
      "name": "辞書形＋のはどうですか",
      "level": "N4",
      "tags": [
        "疑問形",
        "recommendations",
        "nominalizing"
      ],
      "notes": "what about this",
      "example": [
        "毎朝ジョギングをするのはどうですか"
      ],
      "gid": "n4-000132"
    },
    {
      "name": "普通形＋だけじゃなくて、＿＿＿も＿＿＿",
      "level": "N4",
      "tags": [
        "lists",
        "explaining"
      ],
      "notes": "not just this exists, also this",
      "example": [
        "日本のアニメを見たいだけじゃなくて、外国のアニメも見たいです"
      ],
      "gid": "n4-000133"
    },
    {
      "name": "イA＋くないと、＿＿＿",
      "level": "N4",
      "tags": [
        "cause-and-effect",
        "conditions"
      ],
      "notes": "if not this, then",
      "example": [
        "もっと安くないと、誰も買いません"
      ],
      "gid": "n4-000134"
    },
    {
      "name": "(ナA|N)＋じゃないと、＿＿＿",
      "level": "N4",
      "tags": [
        "cause-and-effect",
        "conditions"
      ],
      "notes": "if not this, then",
      "example": [
        "さくら図書館は市民じゃないと本が借りられません"
      ],
      "gid": "n4-000135"
    },
    {
      "name": "ナイ形＋と、＿＿＿",
      "level": "N4",
      "tags": [
        "cause-and-effect",
        "conditions"
      ],
      "notes": "if not this, then",
      "example": [
        "ゆっくり話さないと、聞き取りません"
      ],
      "gid": "n4-000136"
    },
    {
      "name": "テ形＋きます",
      "level": "N4",
      "tags": [
        "explaining",
        "time"
      ],
      "notes": "explaining a past trend",
      "example": [
        "最近交通事故がだんだん増えてきました",
        "最近交通事故がだんだん減ってきました",
        "ガソリンの値段がどんどん増えてきました"
      ],
      "gid": "n4-000137"
    },
    {
      "name": "テ形＋いきます",
      "level": "N4",
      "tags": [
        "explaining",
        "time"
      ],
      "notes": "guessing a future trend",
      "example": [
        "これからも減っていくと思います",
        "これからは増えていくと思います"
      ],
      "gid": "n4-000138"
    },
    {
      "name": "普通形＋ために、＿＿＿",
      "level": "N4",
      "tags": [
        "explaining",
        "cause-and-effect",
        "sentence-connector"
      ],
      "notes": "giving a reason",
      "example": [
        "ここはとても危険なために、立ち入り禁止になりました"
      ],
      "gid": "n4-000139"
    },
    {
      "name": "＿＿＿よね",
      "level": "N3",
      "tags": [
        "explaining",
        "combo"
      ],
      "notes": "don't you know?",
      "example": [
        "このバンド本当にかっこいいよね"
      ],
      "gid": "n3-000140"
    },
    {
      "name": "普通形＋とか＋普通形＋とか＋＿＿＿",
      "level": "N3",
      "tags": [
        "lists"
      ],
      "notes": "list examples",
      "example": [
        "そのレストランはたくさん食べ物を注文できる、ラーメンとか、ハンバーガーとかかな"
      ],
      "gid": "n3-000141"
    },
    {
      "name": "普通形＋(だけ|だけの)",
      "level": "N3",
      "tags": [
        "combo"
      ],
      "notes": "as much as you want, limits to the full extent of what its attached to",
      "example": [
        "今日は飲み放題なので、すきなだけ飲んでください",
        "できるだけ早く走ってください"
      ],
      "gid": "n3-000142"
    },
    {
      "name": "普通形＋(でしょう|だろう)",
      "level": "N3",
      "tags": [
        "疑問形",
        "probability"
      ],
      "notes": "questioning the likelihood of something",
      "example": [
        "今夜雨が降るでしょう"
      ],
      "gid": "n3-000143"
    },
    {
      "name": "N＋から＋N＋にかけて＋＿＿＿",
      "level": "N3",
      "tags": [
        "丁寧語",
        "time"
      ],
      "notes": "a polite form of time boxing instead of まで",
      "example": [
        "明日は夕方から夜にかけて晴れそうだ"
      ],
      "gid": "n3-000144"
    },
    {
      "name": "普通形＋と、(A|V)",
      "level": "N3",
      "tags": [
        "cause-and-effect",
        "probability"
      ],
      "notes": "something 100% of the time results in something else",
      "example": [
        "今夜は寒くなるから、では手袋を持っていくと、便利だよ"
      ],
      "gid": "n3-000145"
    },
    {
      "name": "N＋がきっかけで＋＿＿＿",
      "level": "N3",
      "tags": [
        "cause-and-effect"
      ],
      "notes": "due to; the original cause",
      "example": [
        "アニメがきっかけで、日本語の勉強を始めました"
      ],
      "gid": "n3-000146"
    },
    {
      "name": "(マス形|N)＋っぽい",
      "level": "N3",
      "tags": [
        "nominalizing"
      ],
      "notes": "special vocab to describe a person",
      "example": [
        "私は忘れっぽいせいかくで、よく傘をどこかへ置いてきてしまいます",
        "彼女は男っぽい性格です"
      ],
      "gid": "n3-000147"
    },
    {
      "name": "N＋でも",
      "level": "N3",
      "tags": [
        "conditions"
      ],
      "notes": "even this; indicates a bit of surprise ",
      "example": [
        "かの問題は難しいので、先生でも間違えます"
      ],
      "gid": "n3-000148"
    },
    {
      "name": "N＋に限り",
      "level": "N3",
      "tags": [
        "conditions"
      ],
      "notes": "limited to a condition",
      "example": [
        "この交流会に参加できるのは、外国人に限ります"
      ],
      "gid": "n3-000149"
    },
    {
      "name": "N＋によって",
      "level": "N3",
      "tags": [
        "conditions"
      ],
      "notes": "depending on the ...",
      "example": [
        "味のお好みは国によって違います"
      ],
      "gid": "n3-000150"
    },
    {
      "name": "(辞書形|ナイ形|A|N)＋うちに＋＿＿＿＿",
      "level": "N3",
      "tags": [
        "time",
        "conditions"
      ],
      "notes": "before a condition changes",
      "example": [
        "忘れてしまわないうちに、メモします"
      ],
      "gid": "n3-000151"
    },
    {
      "name": "普通形＋わりに＋＿＿＿＿",
      "level": "N3",
      "tags": [
        "comparisons"
      ],
      "notes": "contrary to ...",
      "example": [
        "あのレストランは高い割に、あまり美味しくなかった"
      ],
      "gid": "n3-000152"
    },
    {
      "name": "＿＿＿＋(が)いいんじゃない",
      "level": "N3",
      "tags": [
        "set-phrase",
        "recommendations"
      ],
      "notes": "giving a recommendation; isn't it?; don't you think?",
      "example": [
        "電子辞書を買わないで、スマホを使えばいいんじゃない"
      ],
      "gid": "n3-000153"
    },
    {
      "name": "(辞書形|ナイ形)＋ようになっている",
      "level": "N3",
      "tags": [
        "set-phrase",
        "cause-and-effect"
      ],
      "notes": "an automatic result of some condition",
      "example": [
        "自動ドアは、ここに立つと開くようになっています"
      ],
      "gid": "n3-000154"
    },
    {
      "name": "N＋こそ|普通形＋からこそ",
      "level": "N3",
      "tags": [
        "cause-and-effect",
        "conditions"
      ],
      "notes": "calling out a specific reason",
      "example": [
        "明日こそ、早く起きよう",
        "毎日仕事をしているからこそ、休みが嬉しいんだよ"
      ],
      "gid": "n3-000155"
    },
    {
      "name": "N＋につき",
      "level": "N3",
      "tags": [
        "丁寧語"
      ],
      "notes": "formal version of due to (だから)",
      "example": [
        "雨天につき、本日のイベントは中止になりました"
      ],
      "gid": "n3-000156"
    },
    {
      "name": "＿＿＿と言うことだ",
      "level": "N3",
      "tags": [
        "set-phrase"
      ],
      "notes": "summarize something heard / some general truth",
      "example": [
        "じゃあ、卒業したら、国へ帰るということですね"
      ],
      "gid": "n3-000157"
    },
    {
      "name": "普通形＋でしょうか",
      "level": "N3",
      "tags": [
        "疑問形",
        "丁寧語"
      ],
      "notes": "wondering something",
      "example": [
        "どのくらい時間が掛かるでしょうか"
      ],
      "gid": "n3-000158"
    },
    {
      "name": "普通形＋はずだ",
      "level": "N3",
      "tags": [
        "combo"
      ],
      "notes": "expectation",
      "example": [
        "9時に出れば11時前に到着できるはずだよ"
      ],
      "gid": "n3-000159"
    },
    {
      "name": "N＋向け",
      "level": "N3",
      "tags": [
        "combo"
      ],
      "notes": "meant for",
      "example": [
        "この漫画は子供向けですが大人が見ても十分面白いです"
      ],
      "gid": "n3-000160"
    },
    {
      "name": "N＋において|N＋における＋N",
      "level": "N3",
      "tags": [
        "丁寧語"
      ],
      "notes": "replacement for で",
      "example": [
        "2024年パーリーにおいて、次回の夏のオリンピックが開かれます",
        "私の健康テーマは、日本における自動車産業の欠点です"
      ],
      "gid": "n3-000161"
    },
    {
      "name": "タ形＋上で|N＋の上で",
      "level": "N3",
      "tags": [
        "丁寧語",
        "time"
      ],
      "notes": "a replacement for てから and あとで",
      "example": [
        "書類の内容を読んだ上で、サインをお願いします"
      ],
      "gid": "n3-000162"
    },
    {
      "name": "てほしい|てもらいたい",
      "level": "N3",
      "tags": [
        "combo",
        "set-phrase"
      ],
      "notes": "something you wish to happen",
      "example": [
        "暑い日が続いています。早く寒くなくてほしい",
        "みんなレストランに行ってもらいたい"
      ],
      "gid": "n3-000163"
    },
    {
      "name": "普通形＋はずがない",
      "level": "N3",
      "tags": [
        "probability",
        "set-phrase"
      ],
      "notes": "an action is impossible, no way it will happen",
      "example": [
        "ソダさんは真面目な人だから、ウソをつくはずがない"
      ],
      "gid": "n3-000164"
    },
    {
      "name": "普通形＋なんて",
      "level": "N3",
      "tags": [
        "explaining",
        "conditions"
      ],
      "notes": "emphasis on an example",
      "example": [
        "新婚旅行がVegasなんて、いいなぁ"
      ],
      "gid": "n3-000165"
    },
    {
      "name": "条件形、辞書形＋ほど",
      "level": "N3",
      "tags": [
        "explaining",
        "conditions",
        "set-phrase"
      ],
      "notes": "more of a specifc thing; the more ___, the more ",
      "example": [
        "練習すればするほど、上手になります",
        "安ければ安いほどいいんですが"
      ],
      "gid": "n3-000166"
    },
    {
      "name": "N(＋助詞)＋でも",
      "level": "N3",
      "tags": [
        "lists",
        "recommendations"
      ],
      "notes": "gives a single example, ignoring the other options",
      "example": [
        "あそこでお茶でも飲みませんか",
        "北海道にでも行こうか"
      ],
      "gid": "n3-000167"
    },
    {
      "name": "こんな・そんな・あんな・どんな＋N",
      "level": "N3",
      "tags": [
        "describing"
      ],
      "notes": "that / this / what kind of; like みたい and のような",
      "example": [
        "あー、かわいい。僕もこんな彼女が欲しいな"
      ],
      "gid": "n3-000168"
    },
    {
      "name": "こんな・そんな・あんな・どんな・こういう・そういう・ああいう・どういう＋ふうに",
      "level": "N3",
      "tags": [
        "describing"
      ],
      "notes": "that kind of style; similiar to ように and みたいに",
      "example": [
        "お休みの日はどんな風に過ごしていますか"
      ],
      "gid": "n3-000169"
    },
    {
      "name": "普通形＋ことで",
      "level": "N3",
      "tags": [
        "explaining",
        "cause-and-effect"
      ],
      "notes": "due to this specific thing",
      "example": [
        "寝る前に日記を書くことで、毎日の生活を見直しています"
      ],
      "gid": "n3-000170"
    },
    {
      "name": "文＋なあ",
      "level": "N3",
      "tags": [
        "seems",
        "explaining"
      ],
      "notes": "letting someone know your personal thoughts; wondering out loud",
      "example": [
        "おなかがすいたなあ、何か食べよう",
        "この映画、面白そうだったなあ",
        "もしお金があったら、家を買いたいなあ"
      ],
      "gid": "n3-000171"
    },
    {
      "name": "(辞書形|ナイ形)＋こと(が|も)ある",
      "level": "N3",
      "tags": [
        "nominalizing",
        "set-phrase"
      ],
      "notes": "this happens, sometimes this happens, this is possible",
      "example": [
        "私はいつも自分で料理を作りますが、たまに作らないことがあります",
        "宿題をしているのはたいてい家でする。図書館ですることもあるよ。"
      ],
      "gid": "n3-000172"
    },
    {
      "name": "N＋にとって",
      "level": "N3",
      "tags": [
        "conditions",
        "explaining"
      ],
      "notes": "something thats true for someone; specific opinions/facts",
      "example": [
        "私にとって、大切な人は妻です"
      ],
      "gid": "n3-000173"
    },
    {
      "name": "普通形＋ことだし",
      "level": "N3",
      "tags": [
        "lists",
        "describing"
      ],
      "notes": "many reasons exist, but this one is good enough; since ___, ___",
      "example": [
        "天気もいいことだし、飲みに行かない？",
        "せっかく日本にいることだし、富士山に登りたいなあと思っています"
      ],
      "gid": "n3-000174"
    },
    {
      "name": "テ形＋くれない",
      "level": "N3",
      "tags": [
        "favors",
        "丁寧語"
      ],
      "notes": "won't you do it for me?",
      "example": [
        "消しゴムを忘れたので、貸してくれない？"
      ],
      "gid": "n3-000175"
    },
    {
      "name": "普通形＋んじゃない",
      "level": "N3",
      "tags": [
        "疑問形"
      ],
      "notes": "i think this, don't you?",
      "example": [
        "顔色が悪いけど、大丈夫？早く帰ったほうがいいんじゃない？",
        "あのカバンが可愛い。でも高いんじゃない？"
      ],
      "gid": "n3-000176"
    },
    {
      "name": "お/ご＋ます/する＋です",
      "level": "N3",
      "tags": [
        "尊敬語"
      ],
      "notes": "creating keigo from nouns",
      "example": [
        "お客様、ご注文はお決まりでしょうか？",
        "お箸をご利用でしょうか？"
      ],
      "gid": "n3-000177"
    },
    {
      "name": "普通形＋場合",
      "level": "N3",
      "tags": [
        "conditions"
      ],
      "notes": "describing a situation, case, circumstance",
      "example": [
        "火事の場合は、１１９番に電話してください"
      ],
      "gid": "n3-000178"
    },
    {
      "name": "ナイ形＋ことには＋ナイ形",
      "level": "N3",
      "tags": [
        "conditions",
        "describing"
      ],
      "notes": "without this, it's impossible or difficult",
      "example": [
        "経験者でないことには、うまくやることはできないだろう"
      ],
      "gid": "n3-000179"
    },
    {
      "name": "たいことがあるんですが",
      "level": "N3",
      "tags": [
        "丁寧語",
        "疑問形",
        "set-phrase"
      ],
      "notes": "polite way of asking for something, asking if it exists",
      "example": [
        "お願いしたいことがあるんですが",
        "ご相談したいことがあるんですが"
      ],
      "gid": "n3-000180"
    },
    {
      "name": "意向形＋とする",
      "level": "N3",
      "tags": [
        "describing",
        "set-phrase",
        "sentence-connector"
      ],
      "notes": "try to, attempt to",
      "example": [
        "寒い朝は、布団から起きようとしても、なかなか出られない"
      ],
      "gid": "n3-000181"
    },
    {
      "name": "(みたい|よう)＋なんですが",
      "level": "N3",
      "tags": [
        "丁寧語",
        "seems",
        "set-phrase"
      ],
      "notes": "politely informing something you noticed",
      "example": [
        "あのう、すみません、これは違うみたいなんですが",
        "あのう、すみません、外に誰か運動していたようなんですが"
      ],
      "gid": "n3-000182"
    },
    {
      "name": "テ形＋いただきたいんですが",
      "level": "N3",
      "tags": [
        "丁寧語",
        "receiving-and-giving",
        "set-phrase"
      ],
      "notes": "polite way of asking for a favor or help",
      "example": [
        "先生、私の作文を直していただきたいんですが",
        "面談の時間を変えていただきたいんですが"
      ],
      "gid": "n3-000183"
    },
    {
      "name": "辞書形＋には",
      "level": "N3",
      "tags": [
        "cause-and-effect",
        "conditions"
      ],
      "notes": "in order to",
      "example": [
        "利用するには、事前の申し込みが必要なんだって",
        "本を借りるには、図書館利用者カードが必要です"
      ],
      "gid": "n3-000184"
    },
    {
      "name": "〜に関わらず",
      "level": "N3",
      "tags": [
        "sure-and-unsure",
        "set-phrase",
        "sentence-connector"
      ],
      "notes": "regardless of",
      "example": [
        "サッカーの試合は天候に関わらず、行われます",
        "お酒を飲む飲まないに関わらず、明日の飲み会の会費は全員３千円です",
        "テストの後は、点数のいい悪いに関わらず、間違えたところをよく復習してください"
      ],
      "gid": "n3-000185"
    },
    {
      "name": "マス形＋次第",
      "level": "N3",
      "tags": [
        "time",
        "conditions"
      ],
      "notes": "as soon as (involves speakers will)",
      "example": [
        "準備が出来次第、発表を始めましょう",
        "仕事が終わり次第、すぐそちらに向かいます"
      ],
      "gid": "n3-000186"
    },
    {
      "name": "(辞書形|N＋の)＋途中",
      "level": "N3",
      "tags": [
        "becoming",
        "explaining",
        "time"
      ],
      "notes": "in the middle of; on the way",
      "example": [
        "学校から渋谷駅向かう途中で、急に雨が降ったきた",
        "電車で会社に行く途中で、急に気分悪くなった"
      ],
      "gid": "n3-000187"
    },
    {
      "name": "N＋を＋N＋として",
      "level": "N3",
      "tags": [
        "describing",
        "set-phrase"
      ],
      "notes": "as a ___; ___ being used as a ___",
      "example": [
        "要らなくなったプリントを紙の飛行機として使っています",
        "この試験では７０点以上を合格とする"
      ],
      "gid": "n3-000188"
    },
    {
      "name": "N＋を背にして",
      "level": "N3",
      "tags": [
        "set-phrase",
        "describing",
        "location"
      ],
      "notes": "with your back facing (used for directions)",
      "example": [
        "じゃ、西口を背にして、本屋と花屋の間の道をまっすぐ行くと、右側にありますよ"
      ],
      "gid": "n3-000189"
    },
    {
      "name": "N＋に沿って",
      "level": "N3",
      "tags": [
        "location",
        "describing"
      ],
      "notes": "along; in accordance with",
      "example": [
        "この道に沿ってずっと行くと、私の家がある"
      ],
      "gid": "n3-000190"
    }
  ],
  "topics": [
    {
      "name": "自己紹介"
    },
    {
      "name": "レストランで"
    },
    {
      "name": "自分の目標や計画"
    },
    {
      "name": "日本の生活"
    },
    {
      "name": "突然のハプニングにあった時"
    },
    {
      "name": "旅行に行く前の準備"
    },
    {
      "name": "日本人の家へ行った時"
    },
    {
      "name": "気持ちを表現すること"
    },
    {
      "name": "観光スポットを説明する"
    },
    {
      "name": "健康するための方法"
    },
    {
      "name": "テレビで気になることを見かけた時"
    },
    {
      "name": "自分の国の行事"
    },
    {
      "name": "日々の生活の中で気になるニュース"
    },
    {
      "name": "新しい環境"
    },
    {
      "name": "食事や買い物をする"
    },
    {
      "name": "レストランや店の紹介"
    },
    {
      "name": "週末の天気予報"
    },
    {
      "name": "時間の有効な使い方"
    },
    {
      "name": "将来のための時間の使い方"
    },
    {
      "name": "職員の説明を聞き取ること"
    },
    {
      "name": "地域にある施設"
    },
    {
      "name": "困っていることを管理人さんに説明"
    }
  ],
  "styles": [
    {
      "name": "カジュアル"
    },
    {
      "name": "丁寧"
    },
    {
      "name": "ビジネス （同僚）"
    },
    {
      "name": "ビジネス （後輩と先輩）"
    }
  ]
}